README.rst
setup.cfg
setup.py
mvnproxy/__init__.py
mvnproxy/__main__.py
mvnproxy/config.py
mvnproxy/mainapp.py
mvnproxy/py.typed
mvnproxy.egg-info/PKG-INFO
mvnproxy.egg-info/SOURCES.txt
mvnproxy.egg-info/dependency_links.txt
mvnproxy.egg-info/entry_points.txt
mvnproxy.egg-info/requires.txt
mvnproxy.egg-info/top_level.txt
mvnproxy/metadata/__init__.py
mvnproxy/metadata/merger.py
mvnproxy/metadata/model.py
mvnproxy/metadata/model_to_xml.py
mvnproxy/metadata/xml_to_model.py
mvnproxy/storage/__init__.py
mvnproxy/storage/construct_maven_metadata.py
mvnproxy/storage/download_artifact.py
mvnproxy/storage/sha1_checksum.py
tests/__init__.py
tests/test_xml_merge.py