Metadata-Version: 1.0
Name: mvnproxy
Version: 1.1.0
Summary: mvnproxy
Home-page: UNKNOWN
Author: Bogdan Mustiata
Author-email: bogdan.mustiata@gmail.com
License: BSD
Platform: UNKNOWN
